{
    "project": "FreeCiv", 
    "projectweb": "http://ca.freeciv.wikia.com/wiki/Freeciv_en_catal%C3%A0", 
    "fileset": {
        "core": {
            "url": "http://svn.gna.org/svn/freeciv/trunk/translations/core/ca.po", 
            "type": "file", 
            "target": "ca.po"
        },
        "nations": {
            "url": "http://svn.gna.org/svn/freeciv/trunk/translations/nations/ca.po", 
            "type": "file", 
            "target": "ca.po"
        }
    },
    "disabled": true
}
