{
    "project": "Organic Maps",
    "license": "Apache-2.0",
    "projectweb": "https://organicmaps.app/ca/",
    "fileset": {
        "organicmaps": {
            "url": "https://github.com/organicmaps/organicmaps.git",
            "type": "git"
        },
        "organicmaps-website": {
            "url": "https://raw.githubusercontent.com/organicmaps/organicmaps.github.io/master/po/content.ca.po",
            "type": "file",
            "target": "organicmaps-website-ca.po"
        },
        "organicmaps-strings": {
            "url": "https://raw.githubusercontent.com/pereorga/software-translations/master/organicmaps/translations/strings.po",
            "type": "file",
            "target": "organicmaps-strings-ca.po"
        }
    }
}
