{
    "project": "TuxPaint",
    "license": "GPL-2.0-only",
    "projectweb": "https://tuxpaint.org/",
    "fileset": {
        "tuxpaint": {
            "url": "https://raw.githubusercontent.com/lliurex/tuxpaint/master/src/po/ca.po",
            "type": "file",
            "target": "ca.po"
        },
        "stamps": {
            "url": "https://raw.githubusercontent.com/lliurex/tuxpaint-config/master/src/po/ca.po",
            "type": "file",
            "target": "ca.po"
        },
        "config": {
            "url": "https://raw.githubusercontent.com/lliurex/tuxpaint-config/master/src/po/ca.po",
            "type": "file",
            "target": "ca.po"
        }
    }
}
